aiob/__init__.py
aiob/__main__.py
aiob/api/Destinations/file_markdown/__init__.py
aiob/api/Destinations/file_markdown/dest_file_markdown.py
aiob/api/Sources/src_file_markdown/__init__.py
aiob/api/Sources/src_file_markdown/src_file_markdown.py
aiob/api/__init__.py
aiob/api/bridge.py
aiob/api/config.py
aiob/api/db.py
aiob/api/model.py
aiob/api/opts.py
aiob/api/plugin_loader.py
aiob/cli/__init__.py
aiob/cli/main.py
aiob-0.0.1.dist-info/entry_points.txt
aiob-0.0.1.dist-info/LICENSE
aiob-0.0.1.dist-info/WHEEL
aiob-0.0.1.dist-info/METADATA
aiob-0.0.1.dist-info/RECORD
