Metadata-Version: 2.1
Name: aiob
Version: 0.0.1
Summary: All In One Bridge.
Home-page: https://www.github.com/Clouder0/AIOB
License: Apache-2.0
Author: clouder
Author-email: clouder0@outlook.com
Requires-Python: >=3.9,<4.0
Classifier: Development Status :: 2 - Pre-Alpha
Classifier: Environment :: Console
Classifier: Framework :: Flake8
Classifier: Framework :: Pytest
Classifier: Framework :: tox
Classifier: Intended Audience :: End Users/Desktop
Classifier: License :: OSI Approved :: Apache Software License
Classifier: Natural Language :: English
Classifier: Operating System :: OS Independent
Classifier: Programming Language :: Python :: 3
Classifier: Programming Language :: Python :: 3.10
Classifier: Programming Language :: Python :: 3.9
Classifier: Topic :: Utilities
Classifier: Typing :: Typed
Requires-Dist: aiofiles (>=0.8.0,<0.9.0)
Requires-Dist: aiohttp (>=3.8.1,<4.0.0)
Requires-Dist: colorama (>=0.4.4,<0.5.0)
Requires-Dist: dynaconf (>=3.1.7,<4.0.0)
Requires-Dist: importlib-metadata (>=4.11.3,<5.0.0); python_version < "3.10"
Requires-Dist: python-frontmatter (>=1.0.0,<2.0.0)
Requires-Dist: shellingham (>=1.4.0,<2.0.0)
Requires-Dist: tinydb (>=4.7.0,<5.0.0)
Requires-Dist: typer[all] (>=0.4.1,<0.5.0)
Project-URL: Repository, https://www.github.com/Clouder0/AIOB
